dico_command/__init__.py
dico_command/addon.py
dico_command/bot.py
dico_command/command.py
dico_command/context.py
dico_command/converter.py
dico_command/decorator.py
dico_command/exception.py
dico_command/utils.py
dico_command-0.0.11.dist-info/LICENSE
dico_command-0.0.11.dist-info/METADATA
dico_command-0.0.11.dist-info/WHEEL
dico_command-0.0.11.dist-info/top_level.txt
dico_command-0.0.11.dist-info/RECORD
