Metadata-Version: 2.1
Name: dico-command
Version: 0.0.11
Summary: Command handler for dico.
Home-page: https://github.com/dico-api/dico-command
Author: eunwoo1104
Author-email: sions04@naver.com
License: UNKNOWN
Platform: UNKNOWN
Classifier: Programming Language :: Python :: 3
Requires-Python: >=3.7
License-File: LICENSE
Requires-Dist: dico-api
